oshino/.env-example
oshino/__init__.py
oshino/agents/__init__.py
oshino/agents/http_agent.py
oshino/agents/subprocess_agent.py
oshino/agents/test_agent.py
oshino/augments/__init__.py
oshino/augments/stats.py
oshino/config.py
oshino/core/__init__.py
oshino/core/heart.py
oshino/core/processor.py
oshino/run.py
oshino/util.py
oshino/version.py
oshino-0.4.0.dist-info/LICENSE
oshino-0.4.0.dist-info/WHEEL
oshino-0.4.0.dist-info/METADATA
oshino-0.4.0.dist-info/RECORD
