Metadata-Version: 2.1
Name: oshino
Version: 0.4.0
Summary: 
Home-page: https://github.com/CodersOfTheNight/oshino
License: MIT
Author: Šarūnas Navickas
Author-email: zaibacu@gmail.com
Requires-Python: >=3.7,<4.0
Classifier: License :: OSI Approved :: MIT License
Classifier: Programming Language :: Python
Classifier: Programming Language :: Python :: 3
Classifier: Programming Language :: Python :: 3.10
Classifier: Programming Language :: Python :: 3.5
Classifier: Programming Language :: Python :: 3.6
Classifier: Programming Language :: Python :: 3.7
Classifier: Programming Language :: Python :: 3.8
Classifier: Programming Language :: Python :: 3.9
Classifier: Programming Language :: Python :: Implementation :: CPython
Classifier: Programming Language :: Python :: Implementation :: PyPy
Requires-Dist: Jinja2 (>=3.0.3,<4.0.0)
Requires-Dist: PyYAML (>=6.0,<7.0)
Requires-Dist: aiohttp (>=3.8.1,<4.0.0)
Requires-Dist: oshino-admin (>=0.2.0,<0.3.0)
Requires-Dist: protobuf (==3.1.0.post1)
Requires-Dist: pytest-asyncio (>=0.17.2,<0.18.0)
Requires-Dist: python-dotenv (>=0.19.2,<0.20.0)
Requires-Dist: raven (>=6.10.0,<7.0.0)
Requires-Dist: requests (>=2.27.1,<3.0.0)
Requires-Dist: riemann-client (==6.3.0)
Project-URL: Repository, https://github.com/CodersOfTheNight/oshino
